MANIFEST.in
README.rst
setup.py
version.txt
Flask_Holster.egg-info/PKG-INFO
Flask_Holster.egg-info/SOURCES.txt
Flask_Holster.egg-info/dependency_links.txt
Flask_Holster.egg-info/not-zip-safe
Flask_Holster.egg-info/requires.txt
Flask_Holster.egg-info/top_level.txt
flask_holster/__init__.py
flask_holster/exts.py
flask_holster/helpers.py
flask_holster/main.py
flask_holster/mime.py
flask_holster/parts.py
flask_holster/simple.py
flask_holster/views.py