Metadata-Version: 1.1
Name: Flask-Holster
Version: 0.3
Summary: Rigid MVC content negotiation for Flask
Home-page: http://github.com/MostAwesomeDude/flask-holster
Author: Corbin Simpson
Author-email: cds@corbinsimpson.com
License: MIT
Platform: any
Classifier: Environment :: Web Environment
Classifier: Intended Audience :: Developers
Classifier: License :: OSI Approved :: MIT License
Classifier: Operating System :: OS Independent
Classifier: Programming Language :: Python
Classifier: Topic :: Internet :: WWW/HTTP :: Dynamic Content
Classifier: Topic :: Software Development :: Libraries :: Python Modules
